conflook/.DS_Store
conflook/__init__.py
conflook/cli.py
conflook/filetypes/.DS_Store
conflook/filetypes/__init__.py
conflook/filetypes/default.py
conflook/filetypes/json.py
conflook/filetypes/toml.py
conflook/filetypes/yaml.py
conflook/utils.py
conflook-0.1.3.dist-info/entry_points.txt
conflook-0.1.3.dist-info/WHEEL
conflook-0.1.3.dist-info/METADATA
conflook-0.1.3.dist-info/licenses/LICENSE
conflook-0.1.3.dist-info/RECORD
