Metadata-Version: 2.1
Name: conflook
Version: v0.1.3
Summary: Inspect ugly config files.
License: MIT
Keywords: cli,configuration,inspect,utility,development
Author: puqeko
Requires-Python: >=3.9
Requires-Dist: click~=8.0
Requires-Dist: pyyaml~=6.0
Requires-Dist: tomlkit~=0.7
